pydelijn/__init__.py
pydelijn/api.py
pydelijn/common.py
pydelijn-1.1.0.dist-info/LICENSE
pydelijn-1.1.0.dist-info/METADATA
pydelijn-1.1.0.dist-info/WHEEL
pydelijn-1.1.0.dist-info/top_level.txt
pydelijn-1.1.0.dist-info/RECORD
