Metadata-Version: 2.1
Name: pydelijn
Version: 1.1.0
Summary: Get realtime info on stop passages of De Lijn (api.delijn.be)
Home-page: https://github.com/bollewolle/pydelijn
Author: bollewolle
Author-email: dev@bollewolle.be
License: MIT
Classifier: Programming Language :: Python
Classifier: Programming Language :: Python :: 3
Classifier: Programming Language :: Python :: 3.5
Classifier: Programming Language :: Python :: 3.6
Classifier: Programming Language :: Python :: 3.7
Classifier: License :: OSI Approved :: MIT License
Classifier: Operating System :: OS Independent
Classifier: Intended Audience :: Developers
Requires-Python: >=3.5.0
License-File: LICENSE
